pycatalyst/__init__.py
pycatalyst/py.typed
pycatalyst-0.0.1.dist-info/licenses/LICENSE
pycatalyst-0.0.1.dist-info/METADATA
pycatalyst-0.0.1.dist-info/WHEEL
pycatalyst-0.0.1.dist-info/top_level.txt
pycatalyst-0.0.1.dist-info/RECORD
