Metadata-Version: 2.4
Name: pycatalyst
Version: 0.0.1
Summary: A modern Python package template — customize this description.
Author-email: Your Name <you@example.com>
License: MIT
Project-URL: Homepage, https://github.com/your-org/pycatalyst
Project-URL: Documentation, https://github.com/your-org/pycatalyst#readme
Project-URL: Repository, https://github.com/your-org/pycatalyst
Project-URL: Issues, https://github.com/your-org/pycatalyst/issues
Keywords: python,template,catalyst
Classifier: Development Status :: 3 - Alpha
Classifier: Intended Audience :: Developers
Classifier: License :: OSI Approved :: MIT License
Classifier: Programming Language :: Python :: 3
Classifier: Programming Language :: Python :: 3.10
Classifier: Programming Language :: Python :: 3.11
Classifier: Programming Language :: Python :: 3.12
Classifier: Programming Language :: Python :: 3.13
Classifier: Typing :: Typed
Requires-Python: >=3.10
License-File: LICENSE
Provides-Extra: dev
Requires-Dist: pytest>=7.4.0; extra == "dev"
Requires-Dist: pytest-cov>=4.1.0; extra == "dev"
Requires-Dist: ruff>=0.4.0; extra == "dev"
Requires-Dist: mypy>=1.8.0; extra == "dev"
Requires-Dist: build>=1.0.0; extra == "dev"
Requires-Dist: twine>=5.0.0; extra == "dev"
Dynamic: license-file
